pybeario/__init__.py
pybeario/colors.py
pybeario-0.0.1.dist-info/LICENSE
pybeario-0.0.1.dist-info/METADATA
pybeario-0.0.1.dist-info/WHEEL
pybeario-0.0.1.dist-info/top_level.txt
pybeario-0.0.1.dist-info/RECORD
