Metadata-Version: 2.1
Name: pybeario
Version: 0.0.1
Summary: Jerbeario's python style package 
Author-email: Jeremy Palmerio <palmerio.jeremy@gmail.com>
Classifier: Programming Language :: Python :: 3
Classifier: License :: OSI Approved :: MIT License
Classifier: Operating System :: OS Independent
Requires-Python: >=3.8
License-File: LICENSE
